sonicslicer/__init__.py
sonicslicer/bulk.py
sonicslicer/colors.py
sonicslicer/decorators.py
sonicslicer/formarts.py
sonicslicer/main.py
sonicslicer/slicer.py
sonicslicer/slicer_exceptions.py
sonicslicer/validators.py
sonicslicer/utils/docs/doc.py
sonicslicer/utils/log/loger.py
sonicslicer-1.0.0.dist-info/licenses/LICENSE
sonicslicer-1.0.0.dist-info/METADATA
sonicslicer-1.0.0.dist-info/WHEEL
sonicslicer-1.0.0.dist-info/entry_points.txt
sonicslicer-1.0.0.dist-info/top_level.txt
sonicslicer-1.0.0.dist-info/RECORD
